{
	"animations": [
		{
			"loop": false,
			"offsets": [
				0,
				-1
			],
			"anim": "firstDeath",
			"fps": 24,
			"name": "BF dies 2",
			"indices": []
		},
		{
			"loop": true,
			"offsets": [
				-6,
				-297
			],
			"anim": "deathLoop",
			"fps": 24,
			"name": "BF dead 2 loop",
			"indices": []
		},
		{
			"loop": false,
			"offsets": [
				-6,
				-259
			],
			"anim": "deathConfirm",
			"fps": 24,
			"name": "BF dead 2 confirm",
			"indices": []
		}
	],
	"no_antialiasing": false,
	"image": "characters/EVISCERATION",
	"position": [
		30,
		380
	],
	"healthicon": "bf",
	"flip_x": true,
	"healthbar_colors": [
		49,
		176,
		209
	],
	"camera_position": [
		0,
		0
	],
	"sing_duration": 4,
	"scale": 1
}