{
	"dialogue": [
		{
			"sound": "e",
			"speed": 0.05,
			"portrait": "nocharleft",
			"boxState": "normal",
			"bg": "defaultLine.cutsceneImage",
			"expression": "default",
			"text": "Good evening, beautiful people."
		},
		{
			"sound": "e",
			"speed": 0.05,
			"portrait": "nocharleft",
			"boxState": "normal",
			"bg": "defaultLine.cutsceneImage",
			"expression": "default",
			"text": "This is KOL News Network with an update on the unusual high-speed chase unfolding along Route 76."
		},
		{
			"sound": "e",
			"speed": 0.05,
			"portrait": "nocharleft",
			"boxState": "normal",
			"bg": "defaultLine.cutsceneImage",
			"expression": "default",
			"text": "Two of the persons atop the involved matte-black limos have been identified as ex-popstar Mommy Mearest..."
		},
		{
			"sound": "e",
			"speed": 0.05,
			"portrait": "nocharleft",
			"boxState": "normal",
			"bg": "defaultLine.cutsceneImage",
			"expression": "default",
			"text": "That's a fuckin' stupid name..."
		},
		{
			"sound": "e",
			"speed": 0.05,
			"portrait": "nocharleft",
			"boxState": "normal",
			"bg": "defaultLine.cutsceneImage",
			"expression": "default",
			"text": "Ahem- and her daughter. with a number of other persons assumed to be affiliates and entourage."
		},
		{
			"sound": "e",
			"speed": 0.05,
			"portrait": "nocharleft",
			"boxState": "normal",
			"bg": "defaultLine.cutsceneImage",
			"expression": "default",
			"text": "Whatever the case, the road there is known to be littered with low-hanging street lights, so caution is advised."
		},
		{
			"sound": "e",
			"speed": 0.05,
			"portrait": "nocharleft",
			"boxState": "angry",
			"bg": "defaultLine.cutsceneImage",
			"expression": "default",
			"text": "Seriously, who the fuck put those there!? There's, like, a twelve mile stretch with no light behind them."
		},
		{
			"sound": "e",
			"speed": 0.05,
			"portrait": "nocharleft",
			"boxState": "normal",
			"bg": "defaultLine.cutsceneImage",
			"expression": "default",
			"text": "More on this high-speed action soon..."
		},
		{
			"sound": "e",
			"speed": 0.05,
			"portrait": "nocharleft",
			"boxState": "normal",
			"bg": "defaultLine.cutsceneImage",
			"expression": "default",
			"text": "Was I supposed to say that? No? I don't give a shit, dude."
		},
		{
			"sound": "dialogue/momText",
			"speed": 0.05,
			"portrait": "mom",
			"boxState": "normal",
			"bg": "defaultLine.cutsceneImage",
			"expression": "default",
			"text": "Not bad, boy...not bad at all."
		},
		{
			"sound": "dialogue/boyfriendText",
			"speed": 0.05,
			"portrait": "bf",
			"boxState": "angry",
			"bg": "defaultLine.cutsceneImage",
			"expression": "pant",
			"text": "This shit...this shit is too much!!"
		},
		{
			"sound": "dialogue/boyfriendText",
			"speed": 0.05,
			"portrait": "bf",
			"boxState": "normal",
			"bg": "defaultLine.cutsceneImage",
			"expression": "pant",
			"text": "I see where those abs come from now..."
		},
		{
			"sound": "dialogue/momText",
			"speed": 0.05,
			"portrait": "mom",
			"boxState": "normal",
			"bg": "defaultLine.cutsceneImage",
			"expression": "smirk",
			"text": "What're you starin' so hard for, boy? You want me??"
		},
		{
			"sound": "dialogue/boyfriendText",
			"speed": 0.05,
			"portrait": "bf",
			"boxState": "normal",
			"bg": "defaultLine.cutsceneImage",
			"expression": "fistBlush",
			"text": "Tch!! As if."
		},
		{
			"sound": "dialogue/gfText",
			"speed": 0.05,
			"portrait": "gf",
			"boxState": "angry",
			"bg": "defaultLine.cutsceneImage",
			"expression": "angry",
			"text": "You're weird as hell mom! Why is it so hard for you and dad to be normal?"
		},
		{
			"sound": "dialogue/gfText",
			"speed": 0.05,
			"portrait": "gf",
			"boxState": "normal",
			"bg": "defaultLine.cutsceneImage",
			"expression": "angry",
			"text": "Crashing my dates,"
		},
		{
			"sound": "dialogue/gfText",
			"speed": 0.05,
			"portrait": "gf",
			"boxState": "normal",
			"bg": "defaultLine.cutsceneImage",
			"expression": "angry",
			"text": "trapping people into televisions,"
		},
		{
			"sound": "dialogue/gfText",
			"speed": 0.05,
			"portrait": "gf",
			"boxState": "normal",
			"bg": "defaultLine.cutsceneImage",
			"expression": "angry",
			"text": "causing someone to smoke themselves from the sheer dread of having to deal with you guys??"
		},
		{
			"sound": "dialogue/gfText",
			"speed": 0.05,
			"portrait": "gf",
			"boxState": "angry",
			"bg": "defaultLine.cutsceneImage",
			"expression": "angry2",
			"text": "It's so annoying!"
		},
		{
			"sound": "",
			"speed": 0.05,
			"portrait": "imps",
			"boxState": "normal",
			"bg": "defaultLine.cutsceneImage",
			"expression": "bojangles",
			"text": "Ms. GF, please calm down suga'!"
		},
		{
			"sound": "",
			"speed": 0.05,
			"portrait": "imps",
			"boxState": "normal",
			"bg": "defaultLine.cutsceneImage",
			"expression": "bubbles",
			"text": "Your parents know what's best for ya...just chill on it."
		},
		{
			"sound": "dialogue/gfText",
			"speed": 0.05,
			"portrait": "gf",
			"boxState": "normal",
			"bg": "defaultLine.cutsceneImage",
			"expression": "grimace",
			"text": "And bringing your simps along!? You're the worst."
		},
		{
			"sound": "dialogue/momText",
			"speed": 0.05,
			"portrait": "mom",
			"boxState": "normal",
			"bg": "defaultLine.cutsceneImage",
			"expression": "seduce",
			"text": "Your boyfriend don't seem to think so. Look at how he's pantin' from just bein' in my presence!"
		},
		{
			"sound": "",
			"speed": 0.105,
			"portrait": "bf",
			"boxState": "normal",
			"bg": "defaultLine.cutsceneImage",
			"expression": "nervous",
			"text": "..."
		},
		{
			"sound": "dialogue/momText",
			"speed": 0.05,
			"portrait": "mom",
			"boxState": "normal",
			"bg": "defaultLine.cutsceneImage",
			"expression": "seduce",
			"text": "Tell me, BF, what is it that you like the most about me?"
		},
		{
			"sound": "dialogue/momText",
			"speed": 0.05,
			"portrait": "mom",
			"boxState": "normal",
			"bg": "defaultLine.cutsceneImage",
			"expression": "seduce",
			"text": "Is it...my scent? The way? My beautiful, long, curly hair...?"
		},
		{
			"sound": "dialogue/momText",
			"speed": 0.05,
			"portrait": "mom",
			"boxState": "normal",
			"bg": "defaultLine.cutsceneImage",
			"expression": "grab",
			"text": "Or perhaps...somethin' else has your eye?"
		},
		{
			"sound": "dialogue/boyfriendText",
			"speed": 0.05,
			"portrait": "bf",
			"boxState": "normal",
			"bg": "defaultLine.cutsceneImage",
			"expression": "defaultBlush",
			"text": "Can we go to the next song please?"
		},
		{
			"sound": "dialogue/gfText",
			"speed": 0.05,
			"portrait": "gf",
			"boxState": "normal",
			"bg": "defaultLine.cutsceneImage",
			"expression": "embarrassed",
			"text": "Why are you dodging the question you manwhore?!"
		},
		{
			"sound": "dialogue/gfText",
			"speed": 0.05,
			"portrait": "gf",
			"boxState": "normal",
			"bg": "defaultLine.cutsceneImage",
			"expression": "think",
			"text": "(I'm losing him. It's so quick but, I'm already losing him.)"
		},
		{
			"sound": "dialogue/gfText",
			"speed": 0.05,
			"portrait": "gf",
			"boxState": "normal",
			"bg": "defaultLine.cutsceneImage",
			"expression": "think",
			"text": "(It can't end like this. BF's gotta remember what he's doing this for...)"
		},
		{
			"sound": "dialogue/momText",
			"speed": 0.05,
			"portrait": "mom",
			"boxState": "normal",
			"bg": "defaultLine.cutsceneImage",
			"expression": "point",
			"text": "Remember, BF. There's a huge difference between a woman, and a little girl."
		},
		{
			"sound": "dialogue/momText",
			"speed": 0.05,
			"portrait": "mom",
			"boxState": "normal",
			"bg": "defaultLine.cutsceneImage",
			"expression": "default",
			"text": "Perhaps this next one can show you what the former can do."
		}
	]
}